tree_sitter/__init__.py
tree_sitter/binding.cp311-win32.pyd
abch_tree_sitter-1.1.4.dist-info/LICENSE
abch_tree_sitter-1.1.4.dist-info/METADATA
abch_tree_sitter-1.1.4.dist-info/WHEEL
abch_tree_sitter-1.1.4.dist-info/top_level.txt
abch_tree_sitter-1.1.4.dist-info/RECORD
