Metadata-Version: 2.1
Name: abch-tree-sitter
Version: 1.1.4
Summary: Python bindings to the Tree-sitter parsing library
Home-page: https://github.com/Ackee-Blockchain/py-tree-sitter
Author: Ackee Blockchain
License: MIT
Project-URL: Source, https://github.com/Ackee-Blockchain/py-tree-sitter
Platform: any
Classifier: License :: OSI Approved :: MIT License
Classifier: Topic :: Software Development :: Compilers
Classifier: Topic :: Text Processing :: Linguistic
Requires-Python: >=3.7
License-File: LICENSE
Requires-Dist: setuptools >=60.0.0 ; python_version >= "3.12"
